xcoscmd/__init__.py
xcoscmd/cos_auth.py
xcoscmd/cos_client.py
xcoscmd/cos_cmd.py
xcoscmd/cos_color.py
xcoscmd/cos_comm.py
xcoscmd/cos_global.py
xcoscmd/cos_threadpool.py
xcoscmd/test.py
xcoscmd-1.8.6.4.dist-info/LICENSE
xcoscmd-1.8.6.4.dist-info/METADATA
xcoscmd-1.8.6.4.dist-info/WHEEL
xcoscmd-1.8.6.4.dist-info/entry_points.txt
xcoscmd-1.8.6.4.dist-info/top_level.txt
xcoscmd-1.8.6.4.dist-info/RECORD
