Metadata-Version: 2.1
Name: xcoscmd
Version: 1.8.6.4
Summary: simple command for cos, forked from https://github.com/tencentyun/coscmd
Home-page: https://www.qcloud.com/
Author: aslinwang
Author-email: dream_jet@qq.com
License: MIT
Platform: UNKNOWN
Requires-Dist: requests (>=2.8)
Requires-Dist: argparse (>=1.4.0)
Requires-Dist: six (>=1.11.0)
Requires-Dist: prettytable (>=0.7)
Requires-Dist: pytz (>=2017.2)
Requires-Dist: datetime (>=4.2)
Requires-Dist: tqdm (>=4.15.0)
Requires-Dist: pyyaml (>=3)
Requires-Dist: cos-python-sdk-v5 (>=1.6.3)
